SynMem/SynMem.py
SynMem/__init__.py
SynMem/SYMClearMemory/ClearMemory.py
SynMem/SYMClearMemory/__init__.py
SynMem/SYMMemoryMaintenance/MemoryMaintenance.py
SynMem/SYMMemoryMaintenance/__init__.py
SynMem/SYMRetrieveMemory/RetrieveMemory.py
SynMem/SYMRetrieveMemory/__init__.py
SynMem/SYMSaveMemory/SaveMemory.py
SynMem/SYMSaveMemory/__init__.py
SynMem/SYMSparkMemory/SparkMemory.py
SynMem/SYMSparkMemory/__init__.py
SynMem/SYMViewMemory/ViewMemory.py
SynMem/SYMViewMemory/__init__.py
synmem-0.1.7.dist-info/METADATA
synmem-0.1.7.dist-info/WHEEL
synmem-0.1.7.dist-info/top_level.txt
synmem-0.1.7.dist-info/RECORD
